<?xml version="1.0"?>
<VOTABLE version="1.1" xsi:schemaLocation="http://www.ivoa.net/xml/VOTable/v1.1" xmlns:xsi="http://www.w3.org/2001/XMLSchema-instance">
  <INFO name="QUERY_STATUS" value="OK"/>
  <RESOURCE type="results">
    <TABLE utype="photdm:PhotometryFilter.transmissionCurve.spectrum">
    <PARAM name="FilterProfileService" value="ivo://svo/fps" ucd="meta.ref.ivorn" utype="PhotometryFilter.fpsIdentifier" datatype="char" arraysize="*"/>
    <PARAM name="filterID" value="COBE/DIRBE.140m" ucd="meta.id" utype="photdm:PhotometryFilter.identifier" datatype="char" arraysize="*"/>
    <PARAM name="WavelengthUnit" value="Angstrom" ucd="meta.unit" utype="PhotometryFilter.SpectralAxis.unit" datatype="char" arraysize="*"/>
    <PARAM name="WavelengthUCD" value="em.wl" ucd="meta.ucd" utype="PhotometryFilter.SpectralAxis.UCD" datatype="char" arraysize="*"/>
    <PARAM name="Description" value="DIRBE 140 micron filter" ucd="meta.note" utype="photdm:PhotometryFilter.description" datatype="char" arraysize="*"/>
    <PARAM name="PhotSystem" value="DIRBE" utype="photdm:PhotometricSystem.description" datatype="char" arraysize="*">
       <DESCRIPTION>Photometric system</DESCRIPTION>
    </PARAM>
    <PARAM name="DetectorType" value="1" utype="photdm:PhotometricSystem.detectorType" datatype="char" arraysize="*">
       <DESCRIPTION>Detector type. 0:Energy counter, 1:Photon counter.</DESCRIPTION>
    </PARAM>
    <PARAM name="Instrument" value="DIRBE" ucd="instr" datatype="char" arraysize="*">
       <DESCRIPTION>Instrument</DESCRIPTION>
    </PARAM>
    <PARAM name="Facility" value="COBE" ucd="instr.obsty" datatype="char" arraysize="*">
       <DESCRIPTION>Observational facility</DESCRIPTION>
    </PARAM>
    <PARAM name="ProfileReference" value="https://lambda.gsfc.nasa.gov/product/cobe/c_spectral_res.cfm" datatype="char" arraysize="*"/>
    <PARAM name="Description" value="DIRBE 140 micron filter" ucd="meta.note" utype="photdm:PhotometryFilter.description" datatype="char" arraysize="*"/>
    <PARAM name="Comments" value="Normalized system (filter + detector) response function." ucd="meta.note" datatype="char" arraysize="*"/>
    <PARAM name="components" value="Filter + Instrument" datatype="char" arraysize="*">
       <DESCRIPTION>Transmission components</DESCRIPTION>
    </PARAM>
    <PARAM name="WavelengthRef" value="1494769.2617707" unit="Angstrom" ucd="em.wl" datatype="float" >
       <DESCRIPTION>Reference wavelength. Defined as the same than the pivot wavelength.</DESCRIPTION>
    </PARAM>
    <PARAM name="WavelengthMean" value="1545961.3299577" unit="Angstrom" ucd="em.wl" utype="photdm:PhotometryFilter.SpectralAxis.Coverage.Location.Value" datatype="float" >
       <DESCRIPTION>Mean wavelength. Defined as integ[x*filter(x) dx]/integ[filter(x) dx]</DESCRIPTION>
    </PARAM>
    <PARAM name="WavelengthEff" value="1419998.3341933" unit="Angstrom" ucd="em.wl.effective" datatype="float" >
       <DESCRIPTION>Effective wavelength. Defined as integ[x*filter(x)*vega(x) dx]/integ[filter(x)*vega(x) dx]</DESCRIPTION>
    </PARAM>
    <PARAM name="WavelengthMin" value="998090" unit="Angstrom" ucd="em.wl;stat.min" utype="photdm:PhotometryFilter.SpectralAxis.Coverage.Bounds.Start" datatype="float" >
       <DESCRIPTION>Minimum filter wavelength. Defined as the first lambda value with a transmission at least 1% of maximum transmission</DESCRIPTION>
    </PARAM>
    <PARAM name="WavelengthMax" value="2639810" unit="Angstrom" ucd="em.wl;stat.max" utype="photdm:PhotometryFilter.SpectralAxis.Coverage.Bounds.Stop" datatype="float" >
       <DESCRIPTION>Maximum filter wavelength. Defined as the last lambda value with a transmission at least 1% of maximum transmission</DESCRIPTION>
    </PARAM>
    <PARAM name="WidthEff" value="414260.47064915" unit="Angstrom" ucd="instr.bandwidth" utype="photdm:PhotometryFilter.SpectralAxis.Coverage.Bounds.Extent" datatype="float" >
       <DESCRIPTION>Effective width. Defined as integ[x*filter(x) dx].\nEquivalent to the horizontal size of a rectangle with height equal to maximum transmission and with the same area that the one covered by the filter transmission curve.</DESCRIPTION>
    </PARAM>
    <PARAM name="WavelengthCen" value="1501616.0714286" unit="Angstrom" ucd="em.wl" datatype="float" >
       <DESCRIPTION>Central wavelength. Defined as the central wavelength between the two points defining FWMH</DESCRIPTION>
    </PARAM>
    <PARAM name="WavelengthPivot" value="1494769.2617707" unit="Angstrom" ucd="em.wl" datatype="float" >
       <DESCRIPTION>Peak wavelength. Defined as sqrt{integ[x*filter(x) dx]/integ[filter(x) dx/x]}</DESCRIPTION>
    </PARAM>
    <PARAM name="WavelengthPeak" value="1531180" unit="Angstrom" ucd="em.wl" datatype="float" >
       <DESCRIPTION>Peak wavelength. Defined as the lambda value with larger transmission</DESCRIPTION>
    </PARAM>
    <PARAM name="WavelengthPhot" value="1448208.1088352" unit="Angstrom" ucd="em.wl" datatype="float" >
       <DESCRIPTION>Photon distribution based effective wavelength. Defined as integ[x^2*filter(x)*vega(x) dx]/integ[x*filter(x)*vega(x) dx]</DESCRIPTION>
    </PARAM>
    <PARAM name="FWHM" value="351402.14285714" unit="Angstrom" ucd="instr.bandwidth" datatype="float" >
       <DESCRIPTION>Full width at half maximum. Defined as the difference between the two wavelengths for which filter transmission is half maximum</DESCRIPTION>
    </PARAM>
    <PARAM name="Fsun" value="0.00000053082223044058" unit="erg/cm2/s/A" ucd="phot.flux.density" datatype="float" >
       <DESCRIPTION>Sun flux</DESCRIPTION>
    </PARAM>
    <PARAM name="PhotCalID" value="COBE/DIRBE.140m/Vega" ucd="meta.id" utype="photdm:PhotCal.identifier" datatype="char" arraysize="*"/>
    <PARAM name="MagSys" value="Vega" ucd="meta.code" utype="photdm:PhotCal.MagnitudeSystem.type" datatype="char" arraysize="*"/>
    <PARAM name="ZeroPoint" value="0.16872510832735" unit="Jy" ucd="phot.flux.density" utype="photdm:PhotCal.ZeroPoint.Flux.value" datatype="float" />
    <PARAM name="ZeroPointUnit" value="Jy" ucd="meta.unit" utype="photdm:PhotCal.ZeroPoint.Flux.unit" datatype="char" arraysize="*"/>
    <PARAM name="ZeroPointType" value="Pogson" ucd="meta.code" utype="photdm:PhotCal.ZeroPoint.type" datatype="char" arraysize="*"/>
      <FIELD name="Wavelength" utype="spec:Data.SpectralAxis.Value" ucd="em.wl" unit="Angstrom" datatype="float"/>
      <FIELD name="Transmission" utype="spec:Data.FluxAxis.Value" ucd="phys.transmission" unit="" datatype="float"/>
      <DATA>
        <TABLEDATA>
          <TR>
            <TD>990350.0</TD>
            <TD>0.00</TD>
          </TR>
          <TR>
            <TD>998090.0</TD>
            <TD>0.01</TD>
          </TR>
          <TR>
            <TD>1005890.0</TD>
            <TD>0.01</TD>
          </TR>
          <TR>
            <TD>1013740.0</TD>
            <TD>0.02</TD>
          </TR>
          <TR>
            <TD>1021660.0</TD>
            <TD>0.02</TD>
          </TR>
          <TR>
            <TD>1029640.0</TD>
            <TD>0.03</TD>
          </TR>
          <TR>
            <TD>1037690.0</TD>
            <TD>0.03</TD>
          </TR>
          <TR>
            <TD>1045790.0</TD>
            <TD>0.04</TD>
          </TR>
          <TR>
            <TD>1053960.0</TD>
            <TD>0.05</TD>
          </TR>
          <TR>
            <TD>1062190.0</TD>
            <TD>0.06</TD>
          </TR>
          <TR>
            <TD>1070490.0</TD>
            <TD>0.08</TD>
          </TR>
          <TR>
            <TD>1078850.0</TD>
            <TD>0.09</TD>
          </TR>
          <TR>
            <TD>1087280.0</TD>
            <TD>0.11</TD>
          </TR>
          <TR>
            <TD>1095770.0</TD>
            <TD>0.12</TD>
          </TR>
          <TR>
            <TD>1104330.0</TD>
            <TD>0.15</TD>
          </TR>
          <TR>
            <TD>1112960.0</TD>
            <TD>0.18</TD>
          </TR>
          <TR>
            <TD>1121650.0</TD>
            <TD>0.21</TD>
          </TR>
          <TR>
            <TD>1130410.0</TD>
            <TD>0.23</TD>
          </TR>
          <TR>
            <TD>1139240.0</TD>
            <TD>0.24</TD>
          </TR>
          <TR>
            <TD>1148140.0</TD>
            <TD>0.26</TD>
          </TR>
          <TR>
            <TD>1157110.0</TD>
            <TD>0.28</TD>
          </TR>
          <TR>
            <TD>1166150.0</TD>
            <TD>0.30</TD>
          </TR>
          <TR>
            <TD>1175260.0</TD>
            <TD>0.32</TD>
          </TR>
          <TR>
            <TD>1184440.0</TD>
            <TD>0.32</TD>
          </TR>
          <TR>
            <TD>1193690.0</TD>
            <TD>0.33</TD>
          </TR>
          <TR>
            <TD>1203020.0</TD>
            <TD>0.34</TD>
          </TR>
          <TR>
            <TD>1212410.0</TD>
            <TD>0.34</TD>
          </TR>
          <TR>
            <TD>1221880.0</TD>
            <TD>0.35</TD>
          </TR>
          <TR>
            <TD>1231430.0</TD>
            <TD>0.35</TD>
          </TR>
          <TR>
            <TD>1241050.0</TD>
            <TD>0.36</TD>
          </TR>
          <TR>
            <TD>1250740.0</TD>
            <TD>0.37</TD>
          </TR>
          <TR>
            <TD>1260510.0</TD>
            <TD>0.38</TD>
          </TR>
          <TR>
            <TD>1270360.0</TD>
            <TD>0.39</TD>
          </TR>
          <TR>
            <TD>1280280.0</TD>
            <TD>0.41</TD>
          </TR>
          <TR>
            <TD>1290280.0</TD>
            <TD>0.43</TD>
          </TR>
          <TR>
            <TD>1300360.0</TD>
            <TD>0.45</TD>
          </TR>
          <TR>
            <TD>1310520.0</TD>
            <TD>0.47</TD>
          </TR>
          <TR>
            <TD>1320760.0</TD>
            <TD>0.49</TD>
          </TR>
          <TR>
            <TD>1331070.0</TD>
            <TD>0.51</TD>
          </TR>
          <TR>
            <TD>1341470.0</TD>
            <TD>0.53</TD>
          </TR>
          <TR>
            <TD>1351950.0</TD>
            <TD>0.55</TD>
          </TR>
          <TR>
            <TD>1362510.0</TD>
            <TD>0.58</TD>
          </TR>
          <TR>
            <TD>1373150.0</TD>
            <TD>0.60</TD>
          </TR>
          <TR>
            <TD>1383880.0</TD>
            <TD>0.63</TD>
          </TR>
          <TR>
            <TD>1394690.0</TD>
            <TD>0.67</TD>
          </TR>
          <TR>
            <TD>1405580.0</TD>
            <TD>0.70</TD>
          </TR>
          <TR>
            <TD>1416560.0</TD>
            <TD>0.73</TD>
          </TR>
          <TR>
            <TD>1427630.0</TD>
            <TD>0.77</TD>
          </TR>
          <TR>
            <TD>1438780.0</TD>
            <TD>0.80</TD>
          </TR>
          <TR>
            <TD>1450020.0</TD>
            <TD>0.84</TD>
          </TR>
          <TR>
            <TD>1461340.0</TD>
            <TD>0.87</TD>
          </TR>
          <TR>
            <TD>1472760.0</TD>
            <TD>0.91</TD>
          </TR>
          <TR>
            <TD>1484260.0</TD>
            <TD>0.95</TD>
          </TR>
          <TR>
            <TD>1495860.0</TD>
            <TD>0.97</TD>
          </TR>
          <TR>
            <TD>1507540.0</TD>
            <TD>0.98</TD>
          </TR>
          <TR>
            <TD>1519320.0</TD>
            <TD>0.99</TD>
          </TR>
          <TR>
            <TD>1531180.0</TD>
            <TD>1.00</TD>
          </TR>
          <TR>
            <TD>1543140.0</TD>
            <TD>1.00</TD>
          </TR>
          <TR>
            <TD>1555200.0</TD>
            <TD>0.97</TD>
          </TR>
          <TR>
            <TD>1567350.0</TD>
            <TD>0.94</TD>
          </TR>
          <TR>
            <TD>1579590.0</TD>
            <TD>0.92</TD>
          </TR>
          <TR>
            <TD>1591930.0</TD>
            <TD>0.88</TD>
          </TR>
          <TR>
            <TD>1604360.0</TD>
            <TD>0.84</TD>
          </TR>
          <TR>
            <TD>1616900.0</TD>
            <TD>0.79</TD>
          </TR>
          <TR>
            <TD>1629530.0</TD>
            <TD>0.74</TD>
          </TR>
          <TR>
            <TD>1642250.0</TD>
            <TD>0.68</TD>
          </TR>
          <TR>
            <TD>1655080.0</TD>
            <TD>0.62</TD>
          </TR>
          <TR>
            <TD>1668010.0</TD>
            <TD>0.55</TD>
          </TR>
          <TR>
            <TD>1681040.0</TD>
            <TD>0.48</TD>
          </TR>
          <TR>
            <TD>1694170.0</TD>
            <TD>0.41</TD>
          </TR>
          <TR>
            <TD>1707410.0</TD>
            <TD>0.37</TD>
          </TR>
          <TR>
            <TD>1720740.0</TD>
            <TD>0.32</TD>
          </TR>
          <TR>
            <TD>1734180.0</TD>
            <TD>0.28</TD>
          </TR>
          <TR>
            <TD>1747730.0</TD>
            <TD>0.24</TD>
          </TR>
          <TR>
            <TD>1761380.0</TD>
            <TD>0.20</TD>
          </TR>
          <TR>
            <TD>1775140.0</TD>
            <TD>0.18</TD>
          </TR>
          <TR>
            <TD>1789010.0</TD>
            <TD>0.15</TD>
          </TR>
          <TR>
            <TD>1802980.0</TD>
            <TD>0.13</TD>
          </TR>
          <TR>
            <TD>1817060.0</TD>
            <TD>0.10</TD>
          </TR>
          <TR>
            <TD>1831260.0</TD>
            <TD>0.10</TD>
          </TR>
          <TR>
            <TD>1845560.0</TD>
            <TD>0.09</TD>
          </TR>
          <TR>
            <TD>1859980.0</TD>
            <TD>0.09</TD>
          </TR>
          <TR>
            <TD>1874510.0</TD>
            <TD>0.08</TD>
          </TR>
          <TR>
            <TD>1889150.0</TD>
            <TD>0.08</TD>
          </TR>
          <TR>
            <TD>1903910.0</TD>
            <TD>0.08</TD>
          </TR>
          <TR>
            <TD>1918780.0</TD>
            <TD>0.07</TD>
          </TR>
          <TR>
            <TD>1933770.0</TD>
            <TD>0.07</TD>
          </TR>
          <TR>
            <TD>1948870.0</TD>
            <TD>0.07</TD>
          </TR>
          <TR>
            <TD>1964100.0</TD>
            <TD>0.07</TD>
          </TR>
          <TR>
            <TD>1979440.0</TD>
            <TD>0.06</TD>
          </TR>
          <TR>
            <TD>1994900.0</TD>
            <TD>0.06</TD>
          </TR>
          <TR>
            <TD>2010480.0</TD>
            <TD>0.05</TD>
          </TR>
          <TR>
            <TD>2026190.0</TD>
            <TD>0.05</TD>
          </TR>
          <TR>
            <TD>2042010.0</TD>
            <TD>0.05</TD>
          </TR>
          <TR>
            <TD>2057970.0</TD>
            <TD>0.04</TD>
          </TR>
          <TR>
            <TD>2074040.0</TD>
            <TD>0.04</TD>
          </TR>
          <TR>
            <TD>2090240.0</TD>
            <TD>0.04</TD>
          </TR>
          <TR>
            <TD>2106570.0</TD>
            <TD>0.03</TD>
          </TR>
          <TR>
            <TD>2123020.0</TD>
            <TD>0.03</TD>
          </TR>
          <TR>
            <TD>2139610.0</TD>
            <TD>0.03</TD>
          </TR>
          <TR>
            <TD>2156320.0</TD>
            <TD>0.03</TD>
          </TR>
          <TR>
            <TD>2173160.0</TD>
            <TD>0.03</TD>
          </TR>
          <TR>
            <TD>2190140.0</TD>
            <TD>0.02</TD>
          </TR>
          <TR>
            <TD>2207250.0</TD>
            <TD>0.02</TD>
          </TR>
          <TR>
            <TD>2224490.0</TD>
            <TD>0.02</TD>
          </TR>
          <TR>
            <TD>2241870.0</TD>
            <TD>0.02</TD>
          </TR>
          <TR>
            <TD>2259380.0</TD>
            <TD>0.02</TD>
          </TR>
          <TR>
            <TD>2277030.0</TD>
            <TD>0.02</TD>
          </TR>
          <TR>
            <TD>2294810.0</TD>
            <TD>0.02</TD>
          </TR>
          <TR>
            <TD>2312740.0</TD>
            <TD>0.02</TD>
          </TR>
          <TR>
            <TD>2330800.0</TD>
            <TD>0.02</TD>
          </TR>
          <TR>
            <TD>2349010.0</TD>
            <TD>0.02</TD>
          </TR>
          <TR>
            <TD>2367360.0</TD>
            <TD>0.02</TD>
          </TR>
          <TR>
            <TD>2385850.0</TD>
            <TD>0.02</TD>
          </TR>
          <TR>
            <TD>2404490.0</TD>
            <TD>0.02</TD>
          </TR>
          <TR>
            <TD>2423270.0</TD>
            <TD>0.02</TD>
          </TR>
          <TR>
            <TD>2442200.0</TD>
            <TD>0.02</TD>
          </TR>
          <TR>
            <TD>2461280.0</TD>
            <TD>0.02</TD>
          </TR>
          <TR>
            <TD>2480500.0</TD>
            <TD>0.02</TD>
          </TR>
          <TR>
            <TD>2499880.0</TD>
            <TD>0.02</TD>
          </TR>
          <TR>
            <TD>2519400.0</TD>
            <TD>0.02</TD>
          </TR>
          <TR>
            <TD>2539080.0</TD>
            <TD>0.01</TD>
          </TR>
          <TR>
            <TD>2558920.0</TD>
            <TD>0.01</TD>
          </TR>
          <TR>
            <TD>2578910.0</TD>
            <TD>0.01</TD>
          </TR>
          <TR>
            <TD>2599050.0</TD>
            <TD>0.01</TD>
          </TR>
          <TR>
            <TD>2619350.0</TD>
            <TD>0.01</TD>
          </TR>
          <TR>
            <TD>2639810.0</TD>
            <TD>0.01</TD>
          </TR>
          <TR>
            <TD>2660430.0</TD>
            <TD>0.00</TD>
          </TR>
        </TABLEDATA>
      </DATA>
    </TABLE>
  </RESOURCE>
</VOTABLE>
