<?xml version="1.0"?>
<VOTABLE version="1.1" xsi:schemaLocation="http://www.ivoa.net/xml/VOTable/v1.1" xmlns:xsi="http://www.w3.org/2001/XMLSchema-instance">
  <INFO name="QUERY_STATUS" value="OK"/>
  <RESOURCE type="results">
    <TABLE utype="photdm:PhotometryFilter.transmissionCurve.spectrum">
    <PARAM name="FilterProfileService" value="ivo://svo/fps" ucd="meta.ref.ivorn" utype="PhotometryFilter.fpsIdentifier" datatype="char" arraysize="*"/>
    <PARAM name="filterID" value="OAJ/JPAS.J0870" ucd="meta.id" utype="photdm:PhotometryFilter.identifier" datatype="char" arraysize="*"/>
    <PARAM name="WavelengthUnit" value="Angstrom" ucd="meta.unit" utype="PhotometryFilter.SpectralAxis.unit" datatype="char" arraysize="*"/>
    <PARAM name="WavelengthUCD" value="em.wl" ucd="meta.ucd" utype="PhotometryFilter.SpectralAxis.UCD" datatype="char" arraysize="*"/>
    <PARAM name="Description" value="JPAS J0870 filter" ucd="meta.note" utype="photdm:PhotometryFilter.description" datatype="char" arraysize="*"/>
    <PARAM name="PhotSystem" value="J-PAS" utype="photdm:PhotometricSystem.description" datatype="char" arraysize="*">
       <DESCRIPTION>Photometric system</DESCRIPTION>
    </PARAM>
    <PARAM name="DetectorType" value="1" utype="photdm:PhotometricSystem.detectorType" datatype="char" arraysize="*">
       <DESCRIPTION>Detector type. 0:Energy counter, 1:Photon counter.</DESCRIPTION>
    </PARAM>
    <PARAM name="Instrument" value="JPCam" ucd="instr" datatype="char" arraysize="*">
       <DESCRIPTION>Instrument</DESCRIPTION>
    </PARAM>
    <PARAM name="Facility" value="OAJ" ucd="instr.obsty" datatype="char" arraysize="*">
       <DESCRIPTION>Observational facility</DESCRIPTION>
    </PARAM>
    <PARAM name="ProfileReference" value="http://www.j-pas.org/survey/jpcam" datatype="char" arraysize="*"/>
    <PARAM name="Description" value="JPAS J0870 filter" ucd="meta.note" utype="photdm:PhotometryFilter.description" datatype="char" arraysize="*"/>
    <PARAM name="Comments" value="Original file creators: J. Varela (jvarela@cefca.es); Toni Marin (amarin@cefca.es)
Date: 2017-03-16
Transmission curve = CCD QE * Filter * Optics * Atmosphere 
Transmission curve of the filter measured by SCHOTT
The 'Optics' include:
- Reflectivity of the mirrors. These values are taken from T80.
- Transmission of the field corrector. Theoretical values.
" ucd="meta.note" datatype="char" arraysize="*"/>
    <PARAM name="components" value="Filter + Instrument + Atmosphere" datatype="char" arraysize="*">
       <DESCRIPTION>Transmission components</DESCRIPTION>
    </PARAM>
    <PARAM name="WavelengthRef" value="8709.0435645519" unit="Angstrom" ucd="em.wl" datatype="double" >
       <DESCRIPTION>Reference wavelength. Defined as the same than the pivot wavelength.</DESCRIPTION>
    </PARAM>
    <PARAM name="WavelengthMean" value="8709.3657064965" unit="Angstrom" ucd="em.wl" utype="photdm:PhotometryFilter.SpectralAxis.Coverage.Location.Value" datatype="double" >
       <DESCRIPTION>Mean wavelength. Defined as integ[x*filter(x) dx]/integ[filter(x) dx]</DESCRIPTION>
    </PARAM>
    <PARAM name="WavelengthEff" value="8708.8922730889" unit="Angstrom" ucd="em.wl.effective" datatype="double" >
       <DESCRIPTION>Effective wavelength. Defined as integ[x*filter(x)*vega(x) dx]/integ[filter(x)*vega(x) dx]</DESCRIPTION>
    </PARAM>
    <PARAM name="WavelengthMin" value="8615.6183729909" unit="Angstrom" ucd="em.wl;stat.min" utype="photdm:PhotometryFilter.SpectralAxis.Coverage.Bounds.Start" datatype="double" >
       <DESCRIPTION>Minimum filter wavelength. Defined as the first lambda value with a transmission at least 1% of maximum transmission</DESCRIPTION>
    </PARAM>
    <PARAM name="WavelengthMax" value="8805.9309930099" unit="Angstrom" ucd="em.wl;stat.max" utype="photdm:PhotometryFilter.SpectralAxis.Coverage.Bounds.Stop" datatype="double" >
       <DESCRIPTION>Maximum filter wavelength. Defined as the last lambda value with a transmission at least 1% of maximum transmission</DESCRIPTION>
    </PARAM>
    <PARAM name="WidthEff" value="145.75533516171" unit="Angstrom" ucd="instr.bandwidth" utype="photdm:PhotometryFilter.SpectralAxis.Coverage.Bounds.Extent" datatype="double" >
       <DESCRIPTION>Effective width. Defined as integ[x*filter(x) dx].\nEquivalent to the horizontal size of a rectangle with height equal to maximum transmission and with the same area that the one covered by the filter transmission curve.</DESCRIPTION>
    </PARAM>
    <PARAM name="WavelengthCen" value="8709.5812205043" unit="Angstrom" ucd="em.wl" datatype="double" >
       <DESCRIPTION>Central wavelength. Defined as the central wavelength between the two points defining FWMH</DESCRIPTION>
    </PARAM>
    <PARAM name="WavelengthPivot" value="8709.0435645519" unit="Angstrom" ucd="em.wl" datatype="double" >
       <DESCRIPTION>Peak wavelength. Defined as sqrt{integ[x*filter(x) dx]/integ[filter(x) dx/x]}</DESCRIPTION>
    </PARAM>
    <PARAM name="WavelengthPeak" value="8681" unit="Angstrom" ucd="em.wl" datatype="double" >
       <DESCRIPTION>Peak wavelength. Defined as the lambda value with larger transmission</DESCRIPTION>
    </PARAM>
    <PARAM name="WavelengthPhot" value="8709.1060388436" unit="Angstrom" ucd="em.wl" datatype="double" >
       <DESCRIPTION>Photon distribution based effective wavelength. Defined as integ[x^2*filter(x)*vega(x) dx]/integ[x*filter(x)*vega(x) dx]</DESCRIPTION>
    </PARAM>
    <PARAM name="FWHM" value="146.53714041251" unit="Angstrom" ucd="instr.bandwidth" datatype="double" >
       <DESCRIPTION>Full width at half maximum. Defined as the difference between the two wavelengths for which filter transmission is half maximum</DESCRIPTION>
    </PARAM>
    <PARAM name="Fsun" value="94.982898576252" unit="erg/cm2/s/A" ucd="phot.flux.density" datatype="double" >
       <DESCRIPTION>Sun flux</DESCRIPTION>
    </PARAM>
    <PARAM name="PhotCalID" value="OAJ/JPAS.J0870/Vega" ucd="meta.id" utype="photdm:PhotCal.identifier" datatype="char" arraysize="*"/>
    <PARAM name="MagSys" value="Vega" ucd="meta.code" utype="photdm:PhotCal.MagnitudeSystem.type" datatype="char" arraysize="*"/>
    <PARAM name="ZeroPoint" value="2208.6960883346" unit="Jy" ucd="phot.flux.density" utype="photdm:PhotCal.ZeroPoint.Flux.value" datatype="double" />
    <PARAM name="ZeroPointUnit" value="Jy" ucd="meta.unit" utype="photdm:PhotCal.ZeroPoint.Flux.unit" datatype="char" arraysize="*"/>
    <PARAM name="ZeroPointType" value="Pogson" ucd="meta.code" utype="photdm:PhotCal.ZeroPoint.type" datatype="char" arraysize="*"/>
      <FIELD name="Wavelength" utype="spec:Data.SpectralAxis.Value" ucd="em.wl" unit="Angstrom" datatype="double"/>
      <FIELD name="Transmission" utype="spec:Data.FluxAxis.Value" ucd="phys.transmission" unit="" datatype="double"/>
      <DATA>
        <TABLEDATA>
          <TR>
            <TD>8584.000000</TD>
            <TD>0.000100</TD>
          </TR>
          <TR>
            <TD>8585.000000</TD>
            <TD>0.000100</TD>
          </TR>
          <TR>
            <TD>8586.000000</TD>
            <TD>0.000100</TD>
          </TR>
          <TR>
            <TD>8587.000000</TD>
            <TD>0.000100</TD>
          </TR>
          <TR>
            <TD>8588.000000</TD>
            <TD>0.000100</TD>
          </TR>
          <TR>
            <TD>8589.000000</TD>
            <TD>0.000100</TD>
          </TR>
          <TR>
            <TD>8590.000000</TD>
            <TD>0.000100</TD>
          </TR>
          <TR>
            <TD>8591.000000</TD>
            <TD>0.000100</TD>
          </TR>
          <TR>
            <TD>8592.000000</TD>
            <TD>0.000100</TD>
          </TR>
          <TR>
            <TD>8593.000000</TD>
            <TD>0.000100</TD>
          </TR>
          <TR>
            <TD>8594.000000</TD>
            <TD>0.000200</TD>
          </TR>
          <TR>
            <TD>8595.000000</TD>
            <TD>0.000200</TD>
          </TR>
          <TR>
            <TD>8596.000000</TD>
            <TD>0.000200</TD>
          </TR>
          <TR>
            <TD>8597.000000</TD>
            <TD>0.000300</TD>
          </TR>
          <TR>
            <TD>8598.000000</TD>
            <TD>0.000300</TD>
          </TR>
          <TR>
            <TD>8599.000000</TD>
            <TD>0.000300</TD>
          </TR>
          <TR>
            <TD>8600.000000</TD>
            <TD>0.000400</TD>
          </TR>
          <TR>
            <TD>8601.000000</TD>
            <TD>0.000400</TD>
          </TR>
          <TR>
            <TD>8602.000000</TD>
            <TD>0.000500</TD>
          </TR>
          <TR>
            <TD>8603.000000</TD>
            <TD>0.000600</TD>
          </TR>
          <TR>
            <TD>8604.000000</TD>
            <TD>0.000700</TD>
          </TR>
          <TR>
            <TD>8605.000000</TD>
            <TD>0.000800</TD>
          </TR>
          <TR>
            <TD>8606.000000</TD>
            <TD>0.000900</TD>
          </TR>
          <TR>
            <TD>8607.000000</TD>
            <TD>0.001000</TD>
          </TR>
          <TR>
            <TD>8608.000000</TD>
            <TD>0.001200</TD>
          </TR>
          <TR>
            <TD>8609.000000</TD>
            <TD>0.001400</TD>
          </TR>
          <TR>
            <TD>8610.000000</TD>
            <TD>0.001600</TD>
          </TR>
          <TR>
            <TD>8611.000000</TD>
            <TD>0.001900</TD>
          </TR>
          <TR>
            <TD>8612.000000</TD>
            <TD>0.002300</TD>
          </TR>
          <TR>
            <TD>8613.000000</TD>
            <TD>0.002800</TD>
          </TR>
          <TR>
            <TD>8614.000000</TD>
            <TD>0.003200</TD>
          </TR>
          <TR>
            <TD>8615.000000</TD>
            <TD>0.003800</TD>
          </TR>
          <TR>
            <TD>8616.000000</TD>
            <TD>0.004500</TD>
          </TR>
          <TR>
            <TD>8617.000000</TD>
            <TD>0.005400</TD>
          </TR>
          <TR>
            <TD>8618.000000</TD>
            <TD>0.006300</TD>
          </TR>
          <TR>
            <TD>8619.000000</TD>
            <TD>0.007500</TD>
          </TR>
          <TR>
            <TD>8620.000000</TD>
            <TD>0.009100</TD>
          </TR>
          <TR>
            <TD>8621.000000</TD>
            <TD>0.011200</TD>
          </TR>
          <TR>
            <TD>8622.000000</TD>
            <TD>0.013700</TD>
          </TR>
          <TR>
            <TD>8623.000000</TD>
            <TD>0.016000</TD>
          </TR>
          <TR>
            <TD>8624.000000</TD>
            <TD>0.019600</TD>
          </TR>
          <TR>
            <TD>8625.000000</TD>
            <TD>0.023500</TD>
          </TR>
          <TR>
            <TD>8626.000000</TD>
            <TD>0.029600</TD>
          </TR>
          <TR>
            <TD>8627.000000</TD>
            <TD>0.035300</TD>
          </TR>
          <TR>
            <TD>8628.000000</TD>
            <TD>0.044500</TD>
          </TR>
          <TR>
            <TD>8629.000000</TD>
            <TD>0.057400</TD>
          </TR>
          <TR>
            <TD>8630.000000</TD>
            <TD>0.072900</TD>
          </TR>
          <TR>
            <TD>8631.000000</TD>
            <TD>0.089100</TD>
          </TR>
          <TR>
            <TD>8632.000000</TD>
            <TD>0.107300</TD>
          </TR>
          <TR>
            <TD>8633.000000</TD>
            <TD>0.127200</TD>
          </TR>
          <TR>
            <TD>8634.000000</TD>
            <TD>0.150600</TD>
          </TR>
          <TR>
            <TD>8635.000000</TD>
            <TD>0.175800</TD>
          </TR>
          <TR>
            <TD>8636.000000</TD>
            <TD>0.201100</TD>
          </TR>
          <TR>
            <TD>8637.000000</TD>
            <TD>0.233200</TD>
          </TR>
          <TR>
            <TD>8638.000000</TD>
            <TD>0.261600</TD>
          </TR>
          <TR>
            <TD>8639.000000</TD>
            <TD>0.295900</TD>
          </TR>
          <TR>
            <TD>8640.000000</TD>
            <TD>0.317500</TD>
          </TR>
          <TR>
            <TD>8641.000000</TD>
            <TD>0.341100</TD>
          </TR>
          <TR>
            <TD>8642.000000</TD>
            <TD>0.360600</TD>
          </TR>
          <TR>
            <TD>8643.000000</TD>
            <TD>0.378700</TD>
          </TR>
          <TR>
            <TD>8644.000000</TD>
            <TD>0.391500</TD>
          </TR>
          <TR>
            <TD>8645.000000</TD>
            <TD>0.400900</TD>
          </TR>
          <TR>
            <TD>8646.000000</TD>
            <TD>0.407600</TD>
          </TR>
          <TR>
            <TD>8647.000000</TD>
            <TD>0.409300</TD>
          </TR>
          <TR>
            <TD>8648.000000</TD>
            <TD>0.410100</TD>
          </TR>
          <TR>
            <TD>8649.000000</TD>
            <TD>0.409800</TD>
          </TR>
          <TR>
            <TD>8650.000000</TD>
            <TD>0.408600</TD>
          </TR>
          <TR>
            <TD>8651.000000</TD>
            <TD>0.408300</TD>
          </TR>
          <TR>
            <TD>8652.000000</TD>
            <TD>0.407900</TD>
          </TR>
          <TR>
            <TD>8653.000000</TD>
            <TD>0.408000</TD>
          </TR>
          <TR>
            <TD>8654.000000</TD>
            <TD>0.408400</TD>
          </TR>
          <TR>
            <TD>8655.000000</TD>
            <TD>0.408700</TD>
          </TR>
          <TR>
            <TD>8656.000000</TD>
            <TD>0.408600</TD>
          </TR>
          <TR>
            <TD>8657.000000</TD>
            <TD>0.408500</TD>
          </TR>
          <TR>
            <TD>8658.000000</TD>
            <TD>0.408100</TD>
          </TR>
          <TR>
            <TD>8659.000000</TD>
            <TD>0.409900</TD>
          </TR>
          <TR>
            <TD>8660.000000</TD>
            <TD>0.408900</TD>
          </TR>
          <TR>
            <TD>8661.000000</TD>
            <TD>0.409500</TD>
          </TR>
          <TR>
            <TD>8662.000000</TD>
            <TD>0.410900</TD>
          </TR>
          <TR>
            <TD>8663.000000</TD>
            <TD>0.411600</TD>
          </TR>
          <TR>
            <TD>8664.000000</TD>
            <TD>0.413400</TD>
          </TR>
          <TR>
            <TD>8665.000000</TD>
            <TD>0.415800</TD>
          </TR>
          <TR>
            <TD>8666.000000</TD>
            <TD>0.416700</TD>
          </TR>
          <TR>
            <TD>8667.000000</TD>
            <TD>0.417700</TD>
          </TR>
          <TR>
            <TD>8668.000000</TD>
            <TD>0.418400</TD>
          </TR>
          <TR>
            <TD>8669.000000</TD>
            <TD>0.419300</TD>
          </TR>
          <TR>
            <TD>8670.000000</TD>
            <TD>0.419600</TD>
          </TR>
          <TR>
            <TD>8671.000000</TD>
            <TD>0.419900</TD>
          </TR>
          <TR>
            <TD>8672.000000</TD>
            <TD>0.419500</TD>
          </TR>
          <TR>
            <TD>8673.000000</TD>
            <TD>0.418900</TD>
          </TR>
          <TR>
            <TD>8674.000000</TD>
            <TD>0.418300</TD>
          </TR>
          <TR>
            <TD>8675.000000</TD>
            <TD>0.418700</TD>
          </TR>
          <TR>
            <TD>8676.000000</TD>
            <TD>0.419300</TD>
          </TR>
          <TR>
            <TD>8677.000000</TD>
            <TD>0.419400</TD>
          </TR>
          <TR>
            <TD>8678.000000</TD>
            <TD>0.419300</TD>
          </TR>
          <TR>
            <TD>8679.000000</TD>
            <TD>0.418200</TD>
          </TR>
          <TR>
            <TD>8680.000000</TD>
            <TD>0.419500</TD>
          </TR>
          <TR>
            <TD>8681.000000</TD>
            <TD>0.420100</TD>
          </TR>
          <TR>
            <TD>8682.000000</TD>
            <TD>0.419700</TD>
          </TR>
          <TR>
            <TD>8683.000000</TD>
            <TD>0.418400</TD>
          </TR>
          <TR>
            <TD>8684.000000</TD>
            <TD>0.419100</TD>
          </TR>
          <TR>
            <TD>8685.000000</TD>
            <TD>0.418600</TD>
          </TR>
          <TR>
            <TD>8686.000000</TD>
            <TD>0.418600</TD>
          </TR>
          <TR>
            <TD>8687.000000</TD>
            <TD>0.418400</TD>
          </TR>
          <TR>
            <TD>8688.000000</TD>
            <TD>0.418100</TD>
          </TR>
          <TR>
            <TD>8689.000000</TD>
            <TD>0.418600</TD>
          </TR>
          <TR>
            <TD>8690.000000</TD>
            <TD>0.418800</TD>
          </TR>
          <TR>
            <TD>8691.000000</TD>
            <TD>0.418700</TD>
          </TR>
          <TR>
            <TD>8692.000000</TD>
            <TD>0.418600</TD>
          </TR>
          <TR>
            <TD>8693.000000</TD>
            <TD>0.418300</TD>
          </TR>
          <TR>
            <TD>8694.000000</TD>
            <TD>0.417900</TD>
          </TR>
          <TR>
            <TD>8695.000000</TD>
            <TD>0.418300</TD>
          </TR>
          <TR>
            <TD>8696.000000</TD>
            <TD>0.419200</TD>
          </TR>
          <TR>
            <TD>8697.000000</TD>
            <TD>0.418100</TD>
          </TR>
          <TR>
            <TD>8698.000000</TD>
            <TD>0.418800</TD>
          </TR>
          <TR>
            <TD>8699.000000</TD>
            <TD>0.417400</TD>
          </TR>
          <TR>
            <TD>8700.000000</TD>
            <TD>0.417100</TD>
          </TR>
          <TR>
            <TD>8701.000000</TD>
            <TD>0.417700</TD>
          </TR>
          <TR>
            <TD>8702.000000</TD>
            <TD>0.417600</TD>
          </TR>
          <TR>
            <TD>8703.000000</TD>
            <TD>0.416800</TD>
          </TR>
          <TR>
            <TD>8704.000000</TD>
            <TD>0.416900</TD>
          </TR>
          <TR>
            <TD>8705.000000</TD>
            <TD>0.418300</TD>
          </TR>
          <TR>
            <TD>8706.000000</TD>
            <TD>0.416000</TD>
          </TR>
          <TR>
            <TD>8707.000000</TD>
            <TD>0.416600</TD>
          </TR>
          <TR>
            <TD>8708.000000</TD>
            <TD>0.417100</TD>
          </TR>
          <TR>
            <TD>8709.000000</TD>
            <TD>0.416600</TD>
          </TR>
          <TR>
            <TD>8710.000000</TD>
            <TD>0.415900</TD>
          </TR>
          <TR>
            <TD>8711.000000</TD>
            <TD>0.415700</TD>
          </TR>
          <TR>
            <TD>8712.000000</TD>
            <TD>0.415400</TD>
          </TR>
          <TR>
            <TD>8713.000000</TD>
            <TD>0.415700</TD>
          </TR>
          <TR>
            <TD>8714.000000</TD>
            <TD>0.414800</TD>
          </TR>
          <TR>
            <TD>8715.000000</TD>
            <TD>0.414400</TD>
          </TR>
          <TR>
            <TD>8716.000000</TD>
            <TD>0.413900</TD>
          </TR>
          <TR>
            <TD>8717.000000</TD>
            <TD>0.414600</TD>
          </TR>
          <TR>
            <TD>8718.000000</TD>
            <TD>0.413100</TD>
          </TR>
          <TR>
            <TD>8719.000000</TD>
            <TD>0.413300</TD>
          </TR>
          <TR>
            <TD>8720.000000</TD>
            <TD>0.413400</TD>
          </TR>
          <TR>
            <TD>8721.000000</TD>
            <TD>0.413100</TD>
          </TR>
          <TR>
            <TD>8722.000000</TD>
            <TD>0.413500</TD>
          </TR>
          <TR>
            <TD>8723.000000</TD>
            <TD>0.412300</TD>
          </TR>
          <TR>
            <TD>8724.000000</TD>
            <TD>0.412900</TD>
          </TR>
          <TR>
            <TD>8725.000000</TD>
            <TD>0.413100</TD>
          </TR>
          <TR>
            <TD>8726.000000</TD>
            <TD>0.412400</TD>
          </TR>
          <TR>
            <TD>8727.000000</TD>
            <TD>0.411600</TD>
          </TR>
          <TR>
            <TD>8728.000000</TD>
            <TD>0.411700</TD>
          </TR>
          <TR>
            <TD>8729.000000</TD>
            <TD>0.410900</TD>
          </TR>
          <TR>
            <TD>8730.000000</TD>
            <TD>0.410700</TD>
          </TR>
          <TR>
            <TD>8731.000000</TD>
            <TD>0.410400</TD>
          </TR>
          <TR>
            <TD>8732.000000</TD>
            <TD>0.408100</TD>
          </TR>
          <TR>
            <TD>8733.000000</TD>
            <TD>0.408600</TD>
          </TR>
          <TR>
            <TD>8734.000000</TD>
            <TD>0.408100</TD>
          </TR>
          <TR>
            <TD>8735.000000</TD>
            <TD>0.408000</TD>
          </TR>
          <TR>
            <TD>8736.000000</TD>
            <TD>0.407200</TD>
          </TR>
          <TR>
            <TD>8737.000000</TD>
            <TD>0.408200</TD>
          </TR>
          <TR>
            <TD>8738.000000</TD>
            <TD>0.405900</TD>
          </TR>
          <TR>
            <TD>8739.000000</TD>
            <TD>0.406400</TD>
          </TR>
          <TR>
            <TD>8740.000000</TD>
            <TD>0.406000</TD>
          </TR>
          <TR>
            <TD>8741.000000</TD>
            <TD>0.406400</TD>
          </TR>
          <TR>
            <TD>8742.000000</TD>
            <TD>0.406300</TD>
          </TR>
          <TR>
            <TD>8743.000000</TD>
            <TD>0.408000</TD>
          </TR>
          <TR>
            <TD>8744.000000</TD>
            <TD>0.407900</TD>
          </TR>
          <TR>
            <TD>8745.000000</TD>
            <TD>0.407500</TD>
          </TR>
          <TR>
            <TD>8746.000000</TD>
            <TD>0.408700</TD>
          </TR>
          <TR>
            <TD>8747.000000</TD>
            <TD>0.407300</TD>
          </TR>
          <TR>
            <TD>8748.000000</TD>
            <TD>0.407600</TD>
          </TR>
          <TR>
            <TD>8749.000000</TD>
            <TD>0.407700</TD>
          </TR>
          <TR>
            <TD>8750.000000</TD>
            <TD>0.405900</TD>
          </TR>
          <TR>
            <TD>8751.000000</TD>
            <TD>0.405800</TD>
          </TR>
          <TR>
            <TD>8752.000000</TD>
            <TD>0.407100</TD>
          </TR>
          <TR>
            <TD>8753.000000</TD>
            <TD>0.406200</TD>
          </TR>
          <TR>
            <TD>8754.000000</TD>
            <TD>0.405400</TD>
          </TR>
          <TR>
            <TD>8755.000000</TD>
            <TD>0.404900</TD>
          </TR>
          <TR>
            <TD>8756.000000</TD>
            <TD>0.405400</TD>
          </TR>
          <TR>
            <TD>8757.000000</TD>
            <TD>0.404100</TD>
          </TR>
          <TR>
            <TD>8758.000000</TD>
            <TD>0.403700</TD>
          </TR>
          <TR>
            <TD>8759.000000</TD>
            <TD>0.403300</TD>
          </TR>
          <TR>
            <TD>8760.000000</TD>
            <TD>0.401500</TD>
          </TR>
          <TR>
            <TD>8761.000000</TD>
            <TD>0.402200</TD>
          </TR>
          <TR>
            <TD>8762.000000</TD>
            <TD>0.402400</TD>
          </TR>
          <TR>
            <TD>8763.000000</TD>
            <TD>0.400600</TD>
          </TR>
          <TR>
            <TD>8764.000000</TD>
            <TD>0.402000</TD>
          </TR>
          <TR>
            <TD>8765.000000</TD>
            <TD>0.400500</TD>
          </TR>
          <TR>
            <TD>8766.000000</TD>
            <TD>0.400300</TD>
          </TR>
          <TR>
            <TD>8767.000000</TD>
            <TD>0.400700</TD>
          </TR>
          <TR>
            <TD>8768.000000</TD>
            <TD>0.398200</TD>
          </TR>
          <TR>
            <TD>8769.000000</TD>
            <TD>0.397300</TD>
          </TR>
          <TR>
            <TD>8770.000000</TD>
            <TD>0.396400</TD>
          </TR>
          <TR>
            <TD>8771.000000</TD>
            <TD>0.392700</TD>
          </TR>
          <TR>
            <TD>8772.000000</TD>
            <TD>0.389500</TD>
          </TR>
          <TR>
            <TD>8773.000000</TD>
            <TD>0.382500</TD>
          </TR>
          <TR>
            <TD>8774.000000</TD>
            <TD>0.375600</TD>
          </TR>
          <TR>
            <TD>8775.000000</TD>
            <TD>0.366800</TD>
          </TR>
          <TR>
            <TD>8776.000000</TD>
            <TD>0.355200</TD>
          </TR>
          <TR>
            <TD>8777.000000</TD>
            <TD>0.334700</TD>
          </TR>
          <TR>
            <TD>8778.000000</TD>
            <TD>0.319500</TD>
          </TR>
          <TR>
            <TD>8779.000000</TD>
            <TD>0.301300</TD>
          </TR>
          <TR>
            <TD>8780.000000</TD>
            <TD>0.278300</TD>
          </TR>
          <TR>
            <TD>8781.000000</TD>
            <TD>0.254700</TD>
          </TR>
          <TR>
            <TD>8782.000000</TD>
            <TD>0.225800</TD>
          </TR>
          <TR>
            <TD>8783.000000</TD>
            <TD>0.204400</TD>
          </TR>
          <TR>
            <TD>8784.000000</TD>
            <TD>0.177200</TD>
          </TR>
          <TR>
            <TD>8785.000000</TD>
            <TD>0.151200</TD>
          </TR>
          <TR>
            <TD>8786.000000</TD>
            <TD>0.126000</TD>
          </TR>
          <TR>
            <TD>8787.000000</TD>
            <TD>0.110200</TD>
          </TR>
          <TR>
            <TD>8788.000000</TD>
            <TD>0.094500</TD>
          </TR>
          <TR>
            <TD>8789.000000</TD>
            <TD>0.081900</TD>
          </TR>
          <TR>
            <TD>8790.000000</TD>
            <TD>0.067400</TD>
          </TR>
          <TR>
            <TD>8791.000000</TD>
            <TD>0.057300</TD>
          </TR>
          <TR>
            <TD>8792.000000</TD>
            <TD>0.049000</TD>
          </TR>
          <TR>
            <TD>8793.000000</TD>
            <TD>0.039700</TD>
          </TR>
          <TR>
            <TD>8794.000000</TD>
            <TD>0.032000</TD>
          </TR>
          <TR>
            <TD>8795.000000</TD>
            <TD>0.026400</TD>
          </TR>
          <TR>
            <TD>8796.000000</TD>
            <TD>0.022500</TD>
          </TR>
          <TR>
            <TD>8797.000000</TD>
            <TD>0.018900</TD>
          </TR>
          <TR>
            <TD>8798.000000</TD>
            <TD>0.015800</TD>
          </TR>
          <TR>
            <TD>8799.000000</TD>
            <TD>0.012700</TD>
          </TR>
          <TR>
            <TD>8800.000000</TD>
            <TD>0.010900</TD>
          </TR>
          <TR>
            <TD>8801.000000</TD>
            <TD>0.009100</TD>
          </TR>
          <TR>
            <TD>8802.000000</TD>
            <TD>0.007500</TD>
          </TR>
          <TR>
            <TD>8803.000000</TD>
            <TD>0.006000</TD>
          </TR>
          <TR>
            <TD>8804.000000</TD>
            <TD>0.005300</TD>
          </TR>
          <TR>
            <TD>8805.000000</TD>
            <TD>0.004700</TD>
          </TR>
          <TR>
            <TD>8806.000000</TD>
            <TD>0.004100</TD>
          </TR>
          <TR>
            <TD>8807.000000</TD>
            <TD>0.003600</TD>
          </TR>
          <TR>
            <TD>8808.000000</TD>
            <TD>0.003000</TD>
          </TR>
          <TR>
            <TD>8809.000000</TD>
            <TD>0.002800</TD>
          </TR>
          <TR>
            <TD>8810.000000</TD>
            <TD>0.002400</TD>
          </TR>
          <TR>
            <TD>8811.000000</TD>
            <TD>0.002000</TD>
          </TR>
          <TR>
            <TD>8812.000000</TD>
            <TD>0.001800</TD>
          </TR>
          <TR>
            <TD>8813.000000</TD>
            <TD>0.001500</TD>
          </TR>
          <TR>
            <TD>8814.000000</TD>
            <TD>0.001400</TD>
          </TR>
          <TR>
            <TD>8815.000000</TD>
            <TD>0.001200</TD>
          </TR>
          <TR>
            <TD>8816.000000</TD>
            <TD>0.001000</TD>
          </TR>
          <TR>
            <TD>8817.000000</TD>
            <TD>0.000800</TD>
          </TR>
          <TR>
            <TD>8818.000000</TD>
            <TD>0.000800</TD>
          </TR>
          <TR>
            <TD>8819.000000</TD>
            <TD>0.000700</TD>
          </TR>
          <TR>
            <TD>8820.000000</TD>
            <TD>0.000600</TD>
          </TR>
          <TR>
            <TD>8821.000000</TD>
            <TD>0.000500</TD>
          </TR>
          <TR>
            <TD>8822.000000</TD>
            <TD>0.000500</TD>
          </TR>
          <TR>
            <TD>8823.000000</TD>
            <TD>0.000400</TD>
          </TR>
          <TR>
            <TD>8824.000000</TD>
            <TD>0.000400</TD>
          </TR>
          <TR>
            <TD>8825.000000</TD>
            <TD>0.000300</TD>
          </TR>
          <TR>
            <TD>8826.000000</TD>
            <TD>0.000300</TD>
          </TR>
          <TR>
            <TD>8827.000000</TD>
            <TD>0.000300</TD>
          </TR>
          <TR>
            <TD>8828.000000</TD>
            <TD>0.000300</TD>
          </TR>
          <TR>
            <TD>8829.000000</TD>
            <TD>0.000200</TD>
          </TR>
          <TR>
            <TD>8830.000000</TD>
            <TD>0.000200</TD>
          </TR>
          <TR>
            <TD>8831.000000</TD>
            <TD>0.000200</TD>
          </TR>
          <TR>
            <TD>8832.000000</TD>
            <TD>0.000200</TD>
          </TR>
          <TR>
            <TD>8833.000000</TD>
            <TD>0.000100</TD>
          </TR>
          <TR>
            <TD>8834.000000</TD>
            <TD>0.000100</TD>
          </TR>
          <TR>
            <TD>8835.000000</TD>
            <TD>0.000100</TD>
          </TR>
          <TR>
            <TD>8836.000000</TD>
            <TD>0.000100</TD>
          </TR>
          <TR>
            <TD>8837.000000</TD>
            <TD>0.000100</TD>
          </TR>
          <TR>
            <TD>8838.000000</TD>
            <TD>0.000100</TD>
          </TR>
          <TR>
            <TD>8839.000000</TD>
            <TD>0.000100</TD>
          </TR>
          <TR>
            <TD>8840.000000</TD>
            <TD>0.000100</TD>
          </TR>
          <TR>
            <TD>8841.000000</TD>
            <TD>0.000100</TD>
          </TR>
          <TR>
            <TD>8842.000000</TD>
            <TD>0.000100</TD>
          </TR>
          <TR>
            <TD>8843.000000</TD>
            <TD>0.000100</TD>
          </TR>
        </TABLEDATA>
      </DATA>
    </TABLE>
  </RESOURCE>
</VOTABLE>
